<annotation>
	<folder>train</folder>
	<filename>00002548.jpg</filename>
	<path>C:\Users\Venkat1257\Desktop\object_detection_demo\data\images\train\00002548.jpg</path>
	<source>
		<database>Unknown</database>
	</source>
	<size>
		<width>600</width>
		<height>420</height>
		<depth>3</depth>
	</size>
	<segmented>0</segmented>
	<object>
		<name>Buddhist Temple</name>
		<pose>Unspecified</pose>
		<truncated>0</truncated>
		<difficult>0</difficult>
		<bndbox>
			<xmin>255</xmin>
			<ymin>142</ymin>
			<xmax>302</xmax>
			<ymax>274</ymax>
		</bndbox>
	</object>
</annotation>
